{
  "subtitles.steam_noise": "Steam noise",
  "item.create_sa.flamethrower_pr_2": "Flamethrower Pr",
  "gui.create_sa.brass_drone_gui.label_inventory": "Inventory",
  "gui.create_sa.vault_module_gui.label_drone_module": "Drone Module",
  "block.create_sa.brass_cube": "Brass Cube",
  "entity.create_sa.brass_cube_r": "Brass Cube",
  "gui.create_sa.vault_module_gui.label_inventory": "Inventory",
  "gui.create_sa.brass_drone_gui.label_drone_module": "Drone Module",
  "item_group.create_sa.create_stuff_additions_tab": "Create Stuff \u0026 Additions",
  "enchantment.create_sa.hellfire": "Hellfire"
}