{
  "citadel.gui.reset": "Reset",
  "citadel.follower.none": "None",
  "item.citadel.citadel_book": "Citadel Book",
  "citadel.gui.cape_type": "Type:",
  "citadel.gui.capes": "Cape Customization",
  "block.citadel.lectern": "Lectern",
  "citadel.gui.orbit_speed": "Rotate Speed",
  "citadel.follower.citadel_gray": "Space Station (Gray)",
  "item.citadel.icon_item": "Icon Item",
  "book.citadel_book.link_example": "Link Example",
  "item.citadel.fancy_item": "Fancy Item",
  "citadel.follower.citadel": "Space Station",
  "book.citadel_book.root": "Citadel Book!!!",
  "citadel.gui.orbit_dist": "Rotate Distance",
  "book.citadel_book.hover_text_pillager_example": "Entity Links are small, cute buttons!",
  "citadel.gui.orbit_height": "Rotate Height",
  "citadel.follower.citadel_red": "Space Station (Red)",
  "item.citadel.effect_item": "Potion Effect",
  "citadel.gui.capes_option": "Cape Customization...",
  "citadel.gui.patreon_customization": "Citadel Patreon Customization",
  "citadel.gui.follower_type": "Type: ",
  "citadel.gui.no_cape": "No Modded Cape",
  "citadel.gui.patreon_rewards_option": "Citadel Patreon Customization..."
}